__init__.py
pyPLCn.py
pyPLCn-1.0.1.dist-info/LICENSE
pyPLCn-1.0.1.dist-info/METADATA
pyPLCn-1.0.1.dist-info/WHEEL
pyPLCn-1.0.1.dist-info/top_level.txt
pyPLCn-1.0.1.dist-info/RECORD
